jarektrading/__init__.py
jarektrading/src/__init__.py
jarektrading/src/jarektrading.py
jarektrading-0.2.7.dist-info/LICENSE.txt
jarektrading-0.2.7.dist-info/METADATA
jarektrading-0.2.7.dist-info/WHEEL
jarektrading-0.2.7.dist-info/top_level.txt
jarektrading-0.2.7.dist-info/RECORD
